{
    "1": {
        "CURSOS": "Habilitação Profissional Técnica de Nível Médio - Modalidade: EAD",
        "DURAÇÃO": "NaN"
    },
    "2": {
        "CURSOS": "Segurança do Trabalho",
        "DURAÇÃO": "NaN"
    },
    "3": {
        "CURSOS": "Especialização Técnica em Segurança do Trabalho na Construção Civil",
        "DURAÇÃO": "DE 60 A 180 DIAS"
    },
    "4": {
        "CURSOS": "Enfermagem",
        "DURAÇÃO": "NaN"
    },
    "5": {
        "CURSOS": "Especialização Técnica em Centro de Material e Esterilização",
        "DURAÇÃO": "DE 60 A 180 DIAS"
    },
    "6": {
        "CURSOS": "Especialização Técnica em Oncologia",
        "DURAÇÃO": "DE 60 A 180 DIAS"
    },
    "7": {
        "CURSOS": "Especialização Técnica em Saúde Pública",
        "DURAÇÃO": "DE 60 A 180 DIAS"
    },
    "8": {
        "CURSOS": "Especialização Técnica em Terapia Intensiva",
        "DURAÇÃO": "DE 60 A 180 DIAS"
    },
    "9": {
        "CURSOS": "Especialização Técnica em Urgência e Emergência / APH",
        "DURAÇÃO": "DE 60 A 180 DIAS"
    },
    "10": {
        "CURSOS": "Especialização Técnica em Saúde do Trabalhador (Segurança do Trabalho)",
        "DURAÇÃO": "DE 60 A 180 DIAS"
    },
    "11": {
        "CURSOS": "ESTÉTICA",
        "DURAÇÃO": "NaN"
    },
    "12": {
        "CURSOS": "Especialização Técnica em Cosmetologia",
        "DURAÇÃO": "DE 60 A 180 DIAS"
    },
    "13": {
        "CURSOS": "T.T.I",
        "DURAÇÃO": "NaN"
    },
    "14": {
        "CURSOS": "Especialização Técnica em Comunicação",
        "DURAÇÃO": "DE 60 A 180 DIAS"
    },
    "15": {
        "CURSOS": "Especialização Técnica em Redação de Contratos",
        "DURAÇÃO": "DE 60 A 180 DIAS"
    },
    "16": {
        "CURSOS": "Especialização Técnica em Mídias Digitais",
        "DURAÇÃO": "DE 60 A 180 DIAS"
    },
    "17": {
        "CURSOS": "Edificações",
        "DURAÇÃO": "NaN"
    },
    "18": {
        "CURSOS": "Especialização Técnica em Programas de Qualidade na Construção Civil",
        "DURAÇÃO": "DE 60 A 180 DIAS"
    },
    "19": {
        "CURSOS": "Logística",
        "DURAÇÃO": "NaN"
    },
    "20": {
        "CURSOS": "Especialização Técnica em Logística Reversa",
        "DURAÇÃO": "DE 60 A 180 DIAS"
    },
    "21": {
        "CURSOS": "Especialização Técnica em Transporte e Distribuição",
        "DURAÇÃO": "DE 60 A 180 DIAS"
    },
    "22": {
        "CURSOS": "Farmácia",
        "DURAÇÃO": "NaN"
    },
    "23": {
        "CURSOS": "Especialização Técnica em Controle da Qualidade em Farmácia",
        "DURAÇÃO": "DE 60 A 180 DIAS"
    }
}